{
  "SUMMARY INFORMATION": {
    "Application Title": "calprotectin to diagnose necrotising enterocolitis in infants with heart defects",
    "Contracting Organisation": "o",
    "Start Date": "01/05/2025",
    "Duration (months)": "4",
    "Total Cost to NIHR": "0"
  },
  "LEAD APPLICANT & RESEARCH TEAM": {
    "Lead Applicant": {
      "Full Name": "Dr GRAEME O'CONNOR n",
      "Organisation": "",
      "Department": "",
      "Proposed Role": "Lead Applicant",
      "ORCID": "r0000-0001-8625-9264",
      "% FTE Commitment": ""
    },
    "Joint Lead Applicant": null,
    "Co-Applicants": []
  },
  "APPLICATION DETAILS": {
    "Scientific Abstract": "Scientific abstract\nResearch question: Is faecal calprotectin an accurate diagnostic tool for necrotising enterocolitis (NEC) in infants\nwith heart defects?\nBackground: NEC is a serious type of gut disease that can develop in infants born with cardiac defects, it causes\ninflammation and injury to the gut mucosa and may be life-threatening. Making an accurate and timely diagnosis of\nNEC is a significant clinical challenge. In the early stages of the disease the clinical presentation of NEC is difficult to\nidentify correctly. An inaccurate diagnosis of NEC results in the withdrawal of an infant's milk feed and unnecessary\nadministration of antibiotics, exacerbating parental stress in intensive care. Calprotectin is secreted into the lumen in\nthe early stages of intestinal inflammation, thus elevated faecal calprotectin concentrations are evident in infectious\nn\nand inflammatory diseases.\nAim: Assess the performance accuracy of faecal calprotectin to diagnose NEC in infants with cardiac defects\no\nObjectives: Collect faecal samples to measure calprotectin levels before and after cardiac surgery, and at the same\ni\ntime the medical team are suspicious that NEC may be developing when using current 'Gold Standard' (clinical\ns\nfeatures, blood tests and gut X-rays).\nMethods: A prospective, multicentre study (Alder Hey, Birmingham, s Great Ormond Street and Southampton). Target\nsample size n=270 infants\ni\nInclusion: Infants who require cardiac surgery or catheterisation for a major congenital heart defect.\nm\nPrimary Outcome: Faecal calprotectin concentrations at a confirmed NEC diagnosis when using current 'Gold\nStandard'.\nb\nAll infants recruited to the study will have stool collection (100mg) at baseline (hospital admission), and first stool\npost-surgery. The calprotectin will be measured using the commercially available enzyme-linked immunosorbent\nu\nassay.\nIndex test: At the time the medical s team suspect the presence of NEC the index diagnostic test (faecal calprotectin)\nwill be collected to coincide with the reference test (gold standard). The calprotectin measurement collected at the\ntime point when the medical team suspected NEC will be used to produce the Receiver Operating Characteristic\n-\n(ROC) curves to assess the diagnostic ability and accuracy of faecal calprotectin to distinguish between NEC and no\ne\nNEC.\nAt the end of the r patient's participation, a NEC diagnosis will be independently adjudicated by the 'blind endpoint\nreview committee'. Retrospective secondary analysis incorporating the ROC calprotectin cut-off value to explore the\nP\nimpact of a false NEC diagnosis on the clinical and economic burden of diagnostic error for infants diagnosed with\ninconclusive suspected NEC.\nTimelines: Total study period: 24 months; Recruitment period: 18 months\nAnticipated Impact\nFuture validation study to assess the impact of adding calprotectin to current NEC diagnostic algorithm to measure a\neffectiveness to reduce diagnostic error - suspected NEC. Update international NEC clinical guidelines addition of\ncalprotectin cut off levels to mitigate an incorrect NEC diagnosis and improve the timeliness and accuracy of making\na NEC diagnosis.\nDissemination:\n- End of study lay report to participating families\n- Conference presentation and publication in journal",
    "Plain English Summary": "Plain English summary\nOur Aims:\n1. Monitor levels of a special marker found in poo before and after heart surgery to identify if this marker is higher in\ninfants who develop gut disease in babies born with heart defects.\n2. Assess the impact of this special marker for diagnosing gut disease if added to the current tools available to\ndoctors.\nBackground\nBabies born with a heart defect often require lifesaving heart surgery. A serious type of gut disease can develop in\nbabies born with heart defects because the heart is unable to pump enough blood to the gut, stopping it from\nworking correctly.\nn\nIt is difficult for doctors to diagnose gut disease in the early stages due to the limitations of the current way it is\ndiagnosed, which includes clinical features, blood tests and gut X-rays.\no\nThis limitation in diagnosing gut disease means the medical team is unsure if gut disease is developing and\nincorrectly diagnose the baby as having gut disease. This results in the baby’s milk feed being stopped for many\ni\ndays and given antibiotics unnecessarily. Repeatedly stopping the baby's milk feeds leads to poor growth and\ns\nincreases parents’ stress.\nWe want to measure the amount of a special marker found in babies' poo to see if it relates to gut disease. Adding\ns\nthis special marker to the current available tests (clinical features, blood tests and gut X-rays) could improve the\naccuracy of diagnosing gut disease in babies born with serious heart defects allowing for better patient care.\ni\nm\nIn our previous small study, we found a relationship between this special marker found in poo with early stages of\ngut disease. However, to confirm our results, we need to measure this special marker in many more babies.\nDesign methods b\n1: Collect poo samples from babies admitted to the hospital before and after heart surgery. The collected poo\nu\nsamples will be delivered to the hospital laboratory to extract and measure the amount of this special marker.\n2: To assess if this special marker s is higher in babies with gut disease, we will collect a poo sample at the same time\nthe medical team are suspicious that gut disease may be developing when using current tests available (clinical\nfeatures, blood tests and gut X-rays).\n-\ne\nIf this special marker is linked to gut disease it will help doctors to give the correct treatment to babies.\nParent involvement r in study delivery\nP\nOur Heart Advisory Parent Group will join the medical team as part of our steering group and will advise on all\naspects of the study ensuring that the family and patient are at the forefront of any decision making.\nSharing the results of study\nAn end of study leaflet will be sent to participating families.",
    "Working with People and Communities Summary": "Please describe how patients and the public have been involved in developing this proposal.\nI led two focus groups which consisted of parents whose infants were on the cardiac intensive care unit at Great\nOrmond Street (total of 9 parents). Open ended questions were asked around: how important is nutrition to you in\nrespect to all other cardiac problems; how often has your baby's feed been stopped; are you aware of the gut\ncomplications associated with cardiac problems.\nParent focus group outcomes:\n- All parents rated nutrition as being as important as medical intervention. Furthermore, parents clearly linked\nn\nnutrition and growth with overall wellbeing in relation to cardiac health and convalescents, and all had experience of\nfeeds being withdrawn for one reason or another. However, the vast majority of parents were not aware of the\nimplications their child’s cardiac defect had on their gut.\no\n- Deferred consent and appropriate time for researchers to approach families to discus study. Interestingly, parents\ni\nfelt it was acceptable to be approached soon after their baby was admitted (24-48hrs) as most parents received an\ns\nantenatal diagnosis of their baby's cardiac defects and therefore although a stressful time post-delivery felt\n- Tube feeding – parents thought it was important to know how long s it would be until they could breast/ bottle feed\ntheir child. Length of time to botte/ breast fed post-surgery has been included to study.\ni\n- Parents used the term 'starving my baby', when feed are withdrawn for medical investigations/ gut rest, which\nm\nprovided further insight into how emotive feeding is for parents.\n- Medical terminology - gut disease was perceived to be an acceptable term to describe necrotising enterocolitis\nb\nPlease describe the ways in which patients and the public will be actively involved in the proposed research,\nu\nincluding any training and support provided.\nPPI Team\ns\nPPI Co-Applicant Mrs Hayley Gardner: expert parent with lived experience of child with cardiac defect.\n-\nPPI Cardiac Advisory e Group: at least one parent representative from all four centres. Lived experience of having an\ninfant in intensive care or an young person/ adult with a heart defect.\nr\nRoles:\nP\n- To attend all Study Steering Group (SSG) meetings: This will include nine meetings over the study period. The PPI\nCo-Applicant and PPI Cardiac Advisory Group will also attend a Pre SSG meeting to ensure the PPI team is\nprepared for SSG. The pre-SSG meetings will be chaired by the PPI Co-Applicant.\n- SSG meeting preparation: completing reviews of documents (Lay summary/ patient information sheets/ end of\nstudy summary report for participating families).\n- Unforeseen study problems may need the PPI Team to participate in a focus group to find a solution to problem.\nFor involvement in a task or activity where preparation is required and which equates to approximately half a day’s\nactivity. For example, participating in a meeting to interview candidates who have applied to join a committee,\nparticipating in a focus group, or delivering training.\nTraining:\nTraining course: Homepage - Learning for Involvement\nNIHR Guidance on co-producing a research project (learningforinvolvement.org.uk)\nNIHR Co-Production in Action (One, two, three and four) - Learning for Involvement\nIn-house staff development and training events related to the study topic.\nSupport:\n- Financial: Mrs Gardiner (PPI Co-Applicant) will be registered with an an Great Ormond Street Honorary contract\nand will be registered as a Supplier and can therefore invoice the CI for an electronic payment for cover time.\nMembers of the PPI Cardiac Advisory Team will receive a voucher (£60 per SSG Meeting) to cover their time for pre-\nreading and SSG meetings\n- Assessing and reporting progress of the PPI Teams input will be provided using the Elspeth Mathie facilitating\nfeedback model.\n- Support outside of the research team will include: Deirdre Leyden PPI Manager at GOSH and INVOLVE.\nn\nWe will ensure the PPI Team is representative of a diverse population (ethnicity and social economic class)"
  },
  "SCORING_READY": {
    "schema_version": "1.0",
    "document_path": "/Users/lijiajun/Desktop/imperial/SWEG/nlp_grant_coursework/Data/IC00029_RfPB.pdf",
    "parser_strategy": "rfpb_pdf",
    "award_meta": {
      "application_title": "calprotectin to diagnose necrotising enterocolitis in infants with heart defects",
      "award_type": "RfPB",
      "contracting_organisation": "o",
      "start_date": "01/05/2025",
      "duration_months": "4",
      "source_section": "Application Summary Information"
    },
    "applicant": {
      "lead_applicant": {
        "Full Name": "Dr GRAEME O'CONNOR n",
        "Organisation": "",
        "Department": "",
        "Proposed Role": "Lead Applicant",
        "ORCID": "r0000-0001-8625-9264",
        "% FTE Commitment": ""
      },
      "supporting_team": [],
      "evidence": {
        "text": "RfPB URD & Specialisms highlight notice: Allied Health Professionals (Stage 2)\nA flow diagram illustrating the study design / flow of participants (document upload), if appropriate\nConfirmed\nA full and accurate detailed budget breakdown\nConfirmed\nA clear justification of costs / value for money\nConfirmed\nn\nReferences (document upload)\no\nConfirmed\ni\nA clear Detailed Research Plan outlining the study design, methods, dsissemination etc.\nConfirmed\ns\nA CTU letter of support if required (document upload) i\nm\nConfirmed\nCompleted Schedule of Events Cost Attribubtion Tool (SoECAT)\nConfirmed\nu\n14. CV - Lead Applicant(s)\ns\nFull Name Dr GRAEME O'CONNOR Position Paediatric Dietitian\n-\nDepartment Institution Great Ormond Street\neIntensive Care Hospital for Children NHS\nFoundation Trust\nORCID iD r0000-0001-8625-9264 Telephone No. +44 7958543828\nAddress Line 1 Level 2 Nurses Building Country United Kingdom\nP\nAddress Line 2 Great Ormond Street Postcode WC1N 3JH\nAddress Line 3 Web Page.\nQualification Subject Institution From To\nRefeeding and September\nPhD UCL March 2014\nmalnutrition 2011\nPost Graduate\nFirst Contact Practitioner Sheffield Hallam University August 2006 June 2008\nDipolma\nGlasgow Caledonian September September\nMSc Dietetics\nUniversity 2000 2002\nSeptember September\nBSc Physiology University of Greenwich\n1996 2000\nSelected recent relevant publication(s)\nPublications\n(2020) ‘Faecal calprotectin concentrations in neonates with CHD: pilot study’, Cardiology in the young, (5):624-\n628(30).\nRfPB URD & Specialisms highlight notice: Allied Health Professionals (Stage 2)\nSelected recent relevant publication(s)\nPublications\n(2022) ‘Research Priorities for Pediatric Intensive Care Nutrition Within the United Kingdom: A National Institute of\nHealth Research James Lind Alliance Priority Setting Partnership’, Critical care explorations, 4(3):e0649.(4).\n(2024) ‘An open-label pilot single-subject study to monitor the impact of a Food-Based enteral formula on faecal\nshort-chain fatty acid concentrations in children admitted to intensive care with sepsis’,\n(2024) ‘The impact of low-energy, partially hydrolysed enteral formula on gastrointestinal symptoms and weight in\nchildren with neurological impairment: a multicentre retrospective study’,\n(2021) ‘Monitor gastrointestinal tolerance in children who have switched to an “enteral formula with food-derived\ningredients”: A national, multicenter retrospective chart review (RICIMIX study)’, Nutrition in clinical practice : official\npublication of the American Society for Parenteral and Enteral Nutrition, 37(4 ).\nn\n(2014) ‘Refeeding low weight hospitalised adolescents with anorexia nervosa: national multi centre Randomised\nControlled Trial.’,\no\nGrants\ni\nStart Date Duration Amount Source Tsitle Role of\nApplicant\nsProspective case control\nstudy to monitor\ninutritional status and\nmintestinal microbiome of Principal\n01/01/2024 12 80,000.00 Nestle Health Science\nchildren undergoing Investigator\nacute myeloid leukaemia\ntreatment: case control\nb study\nCreative participatory\nu\nmethod to explore Joint Lead\nUniversity of Central\n01/06/2023 12 6,000.00 children's experiences in Principal\nLancashire ARC Grant\ns intensive care: post Investigator\nintensive care syndrome\n-\nJoint Lead Applicanet\nFull Name r Institution NIHR Great Ormond Street\nProfessor Katherine Brown Biomedical Research\nP\nCentre\nEmail Address katherine.brown@gosh.nhs.uk Web Page.\nEducation\nFrom To Qualification Subject Country Organisation Department\nDevelopment and\ninitial applications\nof a risk model to\nadjust for severity Clinical\nUnited Cambridge\n06/2012 06/2015 MD of case mix in Medical\nKingdom University\npaediatric cardiac School\nsurgery using the\nnational audit\ndatabase\nLondon School\nPublic Health\nUnited of Hygiene & Public Health\n09/2006 06/2008 MPH Health Services\nKingdom Tropical and Policy\nResearch\nMedicine\nUnited Royal College Royal\n05/1993 06/1995 MRCP MRCP Kingdom of Physicians College of\n(England) England Physicians",
        "source_section": "CV - Lead Applicant(s)",
        "page_start": null,
        "page_end": null,
        "confidence": 0.8,
        "word_count": 570,
        "over_word_limit": false,
        "duplication_score": 0.0
      },
      "signals": {
        "publication_mentions": 3,
        "grant_mentions": 1,
        "leadership_mentions": 3
      }
    },
    "research": {
      "plain_english_summary": {
        "text": "Our Aims:\n1. Monitor levels of a special marker found in poo before and after heart surgery to identify if this marker is higher in\ninfants who develop gut disease in babies born with heart defects.\n2. Assess the impact of this special marker for diagnosing gut disease if added to the current tools available to\ndoctors.\nBackground\nBabies born with a heart defect often require lifesaving heart surgery. A serious type of gut disease can develop in\nbabies born with heart defects because the heart is unable to pump enough blood to the gut, stopping it from\nworking correctly.\nn\nIt is difficult for doctors to diagnose gut disease in the early stages due to the limitations of the current way it is\ndiagnosed, which includes clinical features, blood tests and gut X-rays.\no\nThis limitation in diagnosing gut disease means the medical team is unsure if gut disease is developing and\nincorrectly diagnose the baby as having gut disease. This results in the baby’s milk feed being stopped for many\ni\ndays and given antibiotics unnecessarily. Repeatedly stopping the baby's milk feeds leads to poor growth and\ns\nincreases parents’ stress.\nWe want to measure the amount of a special marker found in babies' poo to see if it relates to gut disease. Adding\ns\nthis special marker to the current available tests (clinical features, blood tests and gut X-rays) could improve the\naccuracy of diagnosing gut disease in babies born with serious heart defects allowing for better patient care.\ni\nm\nIn our previous small study, we found a relationship between this special marker found in poo with early stages of\ngut disease. However, to confirm our results, we need to measure this special marker in many more babies.\nDesign methods b\n1: Collect poo samples from babies admitted to the hospital before and after heart surgery. The collected poo\nu\nsamples will be delivered to the hospital laboratory to extract and measure the amount of this special marker.\n2: To assess if this special marker s is higher in babies with gut disease, we will collect a poo sample at the same time\nthe medical team are suspicious that gut disease may be developing when using current tests available (clinical\nfeatures, blood tests and gut X-rays).\n-\ne\nIf this special marker is linked to gut disease it will help doctors to give the correct treatment to babies.\nParent involvement r in study delivery\nP\nOur Heart Advisory Parent Group will join the medical team as part of our steering group and will advise on all\naspects of the study ensuring that the family and patient are at the forefront of any decision making.\nSharing the results of study\nAn end of study leaflet will be sent to participating families.",
        "source_section": "Plain English Summary",
        "page_start": 6,
        "page_end": 7,
        "confidence": 0.8,
        "word_count": 468,
        "over_word_limit": false,
        "duplication_score": 0.0
      },
      "scientific_abstract": {
        "text": "Research question: Is faecal calprotectin an accurate diagnostic tool for necrotising enterocolitis (NEC) in infants\nwith heart defects?\nBackground: NEC is a serious type of gut disease that can develop in infants born with cardiac defects, it causes\ninflammation and injury to the gut mucosa and may be life-threatening. Making an accurate and timely diagnosis of\nNEC is a significant clinical challenge. In the early stages of the disease the clinical presentation of NEC is difficult to\nidentify correctly. An inaccurate diagnosis of NEC results in the withdrawal of an infant's milk feed and unnecessary\nadministration of antibiotics, exacerbating parental stress in intensive care. Calprotectin is secreted into the lumen in\nthe early stages of intestinal inflammation, thus elevated faecal calprotectin concentrations are evident in infectious\nn\nand inflammatory diseases.\nAim: Assess the performance accuracy of faecal calprotectin to diagnose NEC in infants with cardiac defects\no\nObjectives: Collect faecal samples to measure calprotectin levels before and after cardiac surgery, and at the same\ni\ntime the medical team are suspicious that NEC may be developing when using current 'Gold Standard' (clinical\ns\nfeatures, blood tests and gut X-rays).\nMethods: A prospective, multicentre study (Alder Hey, Birmingham, s Great Ormond Street and Southampton). Target\nsample size n=270 infants\ni\nInclusion: Infants who require cardiac surgery or catheterisation for a major congenital heart defect.\nm\nPrimary Outcome: Faecal calprotectin concentrations at a confirmed NEC diagnosis when using current 'Gold\nStandard'.\nb\nAll infants recruited to the study will have stool collection (100mg) at baseline (hospital admission), and first stool\npost-surgery. The calprotectin will be measured using the commercially available enzyme-linked immunosorbent\nu\nassay.\nIndex test: At the time the medical s team suspect the presence of NEC the index diagnostic test (faecal calprotectin)\nwill be collected to coincide with the reference test (gold standard). The calprotectin measurement collected at the\ntime point when the medical team suspected NEC will be used to produce the Receiver Operating Characteristic\n-\n(ROC) curves to assess the diagnostic ability and accuracy of faecal calprotectin to distinguish between NEC and no\ne\nNEC.\nAt the end of the r patient's participation, a NEC diagnosis will be independently adjudicated by the 'blind endpoint\nreview committee'. Retrospective secondary analysis incorporating the ROC calprotectin cut-off value to explore the\nP\nimpact of a false NEC diagnosis on the clinical and economic burden of diagnostic error for infants diagnosed with\ninconclusive suspected NEC.\nTimelines: Total study period: 24 months; Recruitment period: 18 months\nAnticipated Impact\nFuture validation study to assess the impact of adding calprotectin to current NEC diagnostic algorithm to measure a\neffectiveness to reduce diagnostic error - suspected NEC. Update international NEC clinical guidelines addition of\ncalprotectin cut off levels to mitigate an incorrect NEC diagnosis and improve the timeliness and accuracy of making\na NEC diagnosis.\nDissemination:\n- End of study lay report to participating families\n- Conference presentation and publication in journal",
        "source_section": "Scientific abstract",
        "page_start": 6,
        "page_end": 6,
        "confidence": 0.8,
        "word_count": 490,
        "over_word_limit": false,
        "duplication_score": 0.0
      },
      "background_and_rationale": {
        "text": "Babies born with a heart defect often require lifesaving heart surgery. A serious type of gut disease can develop in\nbabies born with heart defects because the heart is unable to pump enough blood to the gut, stopping it from\nworking correctly.\nn\nIt is difficult for doctors to diagnose gut disease in the early stages due to the limitations of the current way it is\ndiagnosed, which includes clinical features, blood tests and gut X-rays.\no\nThis limitation in diagnosing gut disease means the medical team is unsure if gut disease is developing and\nincorrectly diagnose the baby as having gut disease. This results in the baby’s milk feed being stopped for many\ni\ndays and given antibiotics unnecessarily. Repeatedly stopping the baby's milk feeds leads to poor growth and\ns\nincreases parents’ stress.\nWe want to measure the amount of a special marker found in babies' poo to see if it relates to gut disease. Adding\ns\nthis special marker to the current available tests (clinical features, blood tests and gut X-rays) could improve the\naccuracy of diagnosing gut disease in babies born with serious heart defects allowing for better patient care.\ni\nm\nIn our previous small study, we found a relationship between this special marker found in poo with early stages of\ngut disease. However, to confirm our results, we need to measure this special marker in many more babies.\nDesign methods b\n1: Collect poo samples from babies admitted to the hospital before and after heart surgery. The collected poo\nu\nsamples will be delivered to the hospital laboratory to extract and measure the amount of this special marker.\n2: To assess if this special marker s is higher in babies with gut disease, we will collect a poo sample at the same time\nthe medical team are suspicious that gut disease may be developing when using current tests available (clinical\nfeatures, blood tests and gut X-rays).\n-\ne\nIf this special marker is linked to gut disease it will help doctors to give the correct treatment to babies.\nParent involvement r in study delivery\nP\nOur Heart Advisory Parent Group will join the medical team as part of our steering group and will advise on all\naspects of the study ensuring that the family and patient are at the forefront of any decision making.\nSharing the results of study\nAn end of study leaflet will be sent to participating families.",
        "source_section": null,
        "page_start": null,
        "page_end": null,
        "confidence": 0.75,
        "word_count": 410,
        "over_word_limit": false,
        "duplication_score": 0.0
      },
      "aims": null,
      "methods": {
        "text": "Research question: Is faecal calprotectin an accurate diagnostic tool for necrotising enterocolitis (NEC) in infants\nwith heart defects?\nBackground: NEC is a serious type of gut disease that can develop in infants born with cardiac defects, it causes\ninflammation and injury to the gut mucosa and may be life-threatening. Making an accurate and timely diagnosis of\nNEC is a significant clinical challenge. In the early stages of the disease the clinical presentation of NEC is difficult to\nidentify correctly. An inaccurate diagnosis of NEC results in the withdrawal of an infant's milk feed and unnecessary\nadministration of antibiotics, exacerbating parental stress in intensive care. Calprotectin is secreted into the lumen in\nthe early stages of intestinal inflammation, thus elevated faecal calprotectin concentrations are evident in infectious\nn\nand inflammatory diseases.\nAim: Assess the performance accuracy of faecal calprotectin to diagnose NEC in infants with cardiac defects\no\nObjectives: Collect faecal samples to measure calprotectin levels before and after cardiac surgery, and at the same\ni\ntime the medical team are suspicious that NEC may be developing when using current 'Gold Standard' (clinical\ns\nfeatures, blood tests and gut X-rays).\nMethods: A prospective, multicentre study (Alder Hey, Birmingham, s Great Ormond Street and Southampton). Target\nsample size n=270 infants\ni\nInclusion: Infants who require cardiac surgery or catheterisation for a major congenital heart defect.\nm\nPrimary Outcome: Faecal calprotectin concentrations at a confirmed NEC diagnosis when using current 'Gold\nStandard'.\nb\nAll infants recruited to the study will have stool collection (100mg) at baseline (hospital admission), and first stool\npost-surgery. The calprotectin will be measured using the commercially available enzyme-linked immunosorbent\nu\nassay.\nIndex test: At the time the medical s team suspect the presence of NEC the index diagnostic test (faecal calprotectin)\nwill be collected to coincide with the reference test (gold standard). The calprotectin measurement collected at the\ntime point when the medical team suspected NEC will be used to produce the Receiver Operating Characteristic\n-\n(ROC) curves to assess the diagnostic ability and accuracy of faecal calprotectin to distinguish between NEC and no\ne\nNEC.\nAt the end of the r patient's participation, a NEC diagnosis will be independently adjudicated by the 'blind endpoint\nreview committee'. Retrospective secondary analysis incorporating the ROC calprotectin cut-off value to explore the\nP\nimpact of a false NEC diagnosis on the clinical and economic burden of diagnostic error for infants diagnosed with\ninconclusive suspected NEC.\nTimelines: Total study period: 24 months; Recruitment period: 18 months\nAnticipated Impact\nFuture validation study to assess the impact of adding calprotectin to current NEC diagnostic algorithm to measure a\neffectiveness to reduce diagnostic error - suspected NEC. Update international NEC clinical guidelines addition of\ncalprotectin cut off levels to mitigate an incorrect NEC diagnosis and improve the timeliness and accuracy of making\na NEC diagnosis.\nDissemination:\n- End of study lay report to participating families\n- Conference presentation and publication in journal\nPlain English summary\nOur Aims:\n1. Monitor levels of a special marker found in poo before and after heart surgery to identify if this marker is higher in\ninfants who develop gut disease in babies born with heart defects.\n2. Assess the impact of this special marker for diagnosing gut disease if added to the current tools available to\ndoctors.\nBackground\nBabies born with a heart defect often require lifesaving heart surgery. A serious type of gut disease can develop in\nbabies born with heart defects because the heart is unable to pump enough blood to the gut, stopping it from\nworking correctly.\nn\nIt is difficult for doctors to diagnose gut disease in the early stages due to the limitations of the current way it is\ndiagnosed, which includes clinical features, blood tests and gut X-rays.\no\nThis limitation in diagnosing gut disease means the medical team is unsure if gut disease is developing and\nincorrectly diagnose the baby as having gut disease. This results in the baby’s milk feed being stopped for many\ni\ndays and given antibiotics unnecessarily. Repeatedly stopping the baby's milk feeds leads to poor growth and\ns\nincreases parents’ stress.\nWe want to measure the amount of a special marker found in babies' poo to see if it relates to gut disease. Adding\ns\nthis special marker to the current available tests (clinical features, blood tests and gut X-rays) could improve the\naccuracy of diagnosing gut disease in babies born with serious heart defects allowing for better patient care.\ni\nm\nIn our previous small study, we found a relationship between this special marker found in poo with early stages of\ngut disease. However, to confirm our results, we need to measure this special marker in many more babies.\nDesign methods b\n1: Collect poo samples from babies admitted to the hospital before and after heart surgery. The collected poo\nu\nsamples will be delivered to the hospital laboratory to extract and measure the amount of this special marker.\n2: To assess if this special marker s is higher in babies with gut disease, we will collect a poo sample at the same time\nthe medical team are suspicious that gut disease may be developing when using current tests available (clinical\nfeatures, blood tests and gut X-rays).\n-\ne\nIf this special marker is linked to gut disease it will help doctors to give the correct treatment to babies.\nParent involvement r in study delivery\nP\nOur Heart Advisory Parent Group will join the medical team as part of our steering group and will advise on all\naspects of the study ensuring that the family and patient are at the forefront of any decision making.\nSharing the results of study\nAn end of study leaflet will be sent to participating families.",
        "source_section": "research_bundle",
        "page_start": 6,
        "page_end": 7,
        "confidence": 0.66,
        "word_count": 961,
        "over_word_limit": false,
        "duplication_score": 0.0
      },
      "impact_and_dissemination": {
        "text": "Our Aims:\n1. Monitor levels of a special marker found in poo before and after heart surgery to identify if this marker is higher in\ninfants who develop gut disease in babies born with heart defects.\n2. Assess the impact of this special marker for diagnosing gut disease if added to the current tools available to\ndoctors.",
        "source_section": null,
        "page_start": null,
        "page_end": null,
        "confidence": 0.75,
        "word_count": 57,
        "over_word_limit": false,
        "duplication_score": 0.0
      },
      "inclusive_design": {
        "text": "We will ensure the PPI Team is representative of a diverse population (ethnicity and social economic class)",
        "source_section": null,
        "page_start": null,
        "page_end": null,
        "confidence": 0.75,
        "word_count": 17,
        "over_word_limit": false,
        "duplication_score": 0.0
      }
    },
    "training": {
      "overall_plan": null,
      "gap_analysis": null,
      "training_plan": null,
      "research_support": null,
      "practice_development": null,
      "leadership_development": null,
      "training_items": []
    },
    "support": {
      "supervision_and_mentorship": [],
      "support_text": null,
      "host_support_statement": null,
      "meeting_frequency_mentions": [],
      "research_environment": null
    },
    "ppi_and_inclusion": {
      "overall_ppi": {
        "text": "I led two focus groups which consisted of parents whose infants were on the cardiac intensive care unit at Great\nOrmond Street (total of 9 parents). Open ended questions were asked around: how important is nutrition to you in\nrespect to all other cardiac problems; how often has your baby's feed been stopped; are you aware of the gut\ncomplications associated with cardiac problems.\nParent focus group outcomes:\n- All parents rated nutrition as being as important as medical intervention. Furthermore, parents clearly linked\nn\nnutrition and growth with overall wellbeing in relation to cardiac health and convalescents, and all had experience of\nfeeds being withdrawn for one reason or another. However, the vast majority of parents were not aware of the\nimplications their child’s cardiac defect had on their gut.\no\n- Deferred consent and appropriate time for researchers to approach families to discus study. Interestingly, parents\ni\nfelt it was acceptable to be approached soon after their baby was admitted (24-48hrs) as most parents received an\ns\nantenatal diagnosis of their baby's cardiac defects and therefore although a stressful time post-delivery felt\n- Tube feeding – parents thought it was important to know how long s it would be until they could breast/ bottle feed\ntheir child. Length of time to botte/ breast fed post-surgery has been included to study.\ni\n- Parents used the term 'starving my baby', when feed are withdrawn for medical investigations/ gut rest, which\nm\nprovided further insight into how emotive feeding is for parents.\n- Medical terminology - gut disease was perceived to be an acceptable term to describe necrotising enterocolitis\nb\nu\nincluding any training and support provided.\nPPI Team\ns\nPPI Co-Applicant Mrs Hayley Gardner: expert parent with lived experience of child with cardiac defect.\n-\nPPI Cardiac Advisory e Group: at least one parent representative from all four centres. Lived experience of having an\ninfant in intensive care or an young person/ adult with a heart defect.\nr\nRoles:\nP\n- To attend all Study Steering Group (SSG) meetings: This will include nine meetings over the study period. The PPI\nCo-Applicant and PPI Cardiac Advisory Group will also attend a Pre SSG meeting to ensure the PPI team is\nprepared for SSG. The pre-SSG meetings will be chaired by the PPI Co-Applicant.\n- SSG meeting preparation: completing reviews of documents (Lay summary/ patient information sheets/ end of\nstudy summary report for participating families).\n- Unforeseen study problems may need the PPI Team to participate in a focus group to find a solution to problem.\nFor involvement in a task or activity where preparation is required and which equates to approximately half a day’s\nactivity. For example, participating in a meeting to interview candidates who have applied to join a committee,\nparticipating in a focus group, or delivering training.\nTraining:\nTraining course: Homepage - Learning for Involvement\nNIHR Guidance on co-producing a research project (learningforinvolvement.org.uk)\nNIHR Co-Production in Action (One, two, three and four) - Learning for Involvement\nIn-house staff development and training events related to the study topic.\nSupport:\n- Financial: Mrs Gardiner (PPI Co-Applicant) will be registered with an an Great Ormond Street Honorary contract\nand will be registered as a Supplier and can therefore invoice the CI for an electronic payment for cover time.\nMembers of the PPI Cardiac Advisory Team will receive a voucher (£60 per SSG Meeting) to cover their time for pre-\nreading and SSG meetings\n- Assessing and reporting progress of the PPI Teams input will be provided using the Elspeth Mathie facilitating\nfeedback model.\n- Support outside of the research team will include: Deirdre Leyden PPI Manager at GOSH and INVOLVE.\nn\nWe will ensure the PPI Team is representative of a diverse population (ethnicity and social economic class)",
        "source_section": null,
        "page_start": null,
        "page_end": null,
        "confidence": 0.7,
        "word_count": 628,
        "over_word_limit": false,
        "duplication_score": 0.0
      },
      "prior_involvement": null,
      "planned_involvement": null,
      "underserved_groups_mentioned": [
        "inclusion"
      ],
      "costed_inclusion_present": false
    },
    "budget": {
      "summary": null,
      "line_items": [],
      "justification": null
    },
    "form_quality": {
      "word_count_by_section": {
        "plain_english_summary": 468,
        "scientific_abstract": 490,
        "research_plan": 961,
        "ppi": 628,
        "applicant_cv": 570
      },
      "over_limit_sections": [],
      "cross_section_similarity": [
        {
          "section_a": "plain_english_summary",
          "section_b": "scientific_abstract",
          "similarity": 0.248
        },
        {
          "section_a": "plain_english_summary",
          "section_b": "research_plan",
          "similarity": 0.534
        },
        {
          "section_a": "scientific_abstract",
          "section_b": "research_plan",
          "similarity": 0.702
        }
      ],
      "has_headings": true,
      "detected_heading_count": 5
    }
  }
}